torch_build_nn/_VF.py
torch_build_nn/__config__.py
torch_build_nn/__future__.py
torch_build_nn/__init__.py
torch_build_nn/_appdirs.py
torch_build_nn/_classes.py
torch_build_nn/_compile.py
torch_build_nn/_custom_ops.py
torch_build_nn/_deploy.py
torch_build_nn/_guards.py
torch_build_nn/_jit_internal.py
torch_build_nn/_linalg_utils.py
torch_build_nn/_lobpcg.py
torch_build_nn/_lowrank.py
torch_build_nn/_meta_registrations.py
torch_build_nn/_namedtensor_internals.py
torch_build_nn/_ops.py
torch_build_nn/_python_dispatcher.py
torch_build_nn/_sources.py
torch_build_nn/_storage_docs.py
torch_build_nn/_tensor.py
torch_build_nn/_tensor_docs.py
torch_build_nn/_tensor_str.py
torch_build_nn/_torch_docs.py
torch_build_nn/_utils.py
torch_build_nn/_utils_internal.py
torch_build_nn/_vmap_internals.py
torch_build_nn/_weights_only_unpickler.py
torch_build_nn/functional.py
torch_build_nn/hub.py
torch_build_nn/library.py
torch_build_nn/overrides.py
torch_build_nn/quasirandom.py
torch_build_nn/random.py
torch_build_nn/return_types.py
torch_build_nn/serialization.py
torch_build_nn/storage.py
torch_build_nn/torch_version.py
torch_build_nn/types.py
torch_build_nn/_awaits/__init__.py
torch_build_nn/_custom_op/__init__.py
torch_build_nn/_custom_op/autograd.py
torch_build_nn/_custom_op/functional.py
torch_build_nn/_custom_op/impl.py
torch_build_nn/_decomp/__init__.py
torch_build_nn/_decomp/decompositions.py
torch_build_nn/_decomp/decompositions_for_jvp.py
torch_build_nn/_decomp/decompositions_for_rng.py
torch_build_nn/_dispatch/__init__.py
torch_build_nn/_dispatch/python.py
torch_build_nn/_dynamo/__init__.py
torch_build_nn/_dynamo/allowed_functions.py
torch_build_nn/_dynamo/bytecode_analysis.py
torch_build_nn/_dynamo/bytecode_transformation.py
torch_build_nn/_dynamo/cache_size.py
torch_build_nn/_dynamo/codegen.py
torch_build_nn/_dynamo/compiled_autograd.py
torch_build_nn/_dynamo/comptime.py
torch_build_nn/_dynamo/config.py
torch_build_nn/_dynamo/config_utils.py
torch_build_nn-0.1.16.dist-info/METADATA
torch_build_nn-0.1.16.dist-info/WHEEL
torch_build_nn-0.1.16.dist-info/top_level.txt
torch_build_nn-0.1.16.dist-info/RECORD
