Metadata-Version: 2.1
Name: torch-build-nn
Version: 0.1.16
Requires-Dist: filelock
Requires-Dist: typing-extensions
Requires-Dist: sympy
Requires-Dist: networkx
Requires-Dist: jinja2
Requires-Dist: fsspec
